LICENSE
MANIFEST.in
README.rst
setup.cfg
setup.py
drf_micro_auth.egg-info/PKG-INFO
drf_micro_auth.egg-info/SOURCES.txt
drf_micro_auth.egg-info/dependency_links.txt
drf_micro_auth.egg-info/requires.txt
drf_micro_auth.egg-info/top_level.txt
users/__init__.py
users/api_services.py
users/apps.py
users/models.py
users/rules.py
users/serializers.py
users/services.py
users/urls.py
users/views.py
users/migrations/0001_initial.py
users/migrations/0002_auto_20201017_1247.py
users/migrations/__init__.py
users/templates/users/reset_password_mail.html
users/tests/__init__.py
users/tests/test_users_models.py
users/tests/test_users_rules.py
users/tests/test_users_serializers.py
users/tests/test_users_views.py